objectron/__init__.py
objectron/controllers.py
objectron/exceptions.py
objectron/objectron.py
objectron/proxy.py
objectron/replace.py
objectron/wrappers.py
objectron_decorators/__init__.py
objectron_decorators/decorators.py
objectron-1.0.5.dist-info/LICENSE
objectron-1.0.5.dist-info/METADATA
objectron-1.0.5.dist-info/WHEEL
objectron-1.0.5.dist-info/top_level.txt
objectron-1.0.5.dist-info/RECORD
