Metadata-Version: 2.1
Name: objectron
Version: 1.0.5
Summary: A powerful Python package for transforming and tracking object references
Home-page: https://github.com/kairos-xx/objectron
Author: Joao Lopes
Author-email: Joao Lopes <joaoslopes@gmail.com>
License: MIT License
Project-URL: Homepage, https://github.com/kairos-xx/objectron
Project-URL: Repository, https://github.com/kairos-xx/objectron.git
Keywords: object,transformation,tracking,proxy
Classifier: Programming Language :: Python :: 3
Classifier: License :: OSI Approved :: MIT License
Classifier: Operating System :: OS Independent
Requires-Python: >=3.11
License-File: LICENSE
